randomade/__init__.py
randomade/main.py
randomade-1.5.2.dist-info/METADATA
randomade-1.5.2.dist-info/WHEEL
randomade-1.5.2.dist-info/top_level.txt
randomade-1.5.2.dist-info/RECORD
