Metadata-Version: 2.2
Name: randomade
Version: 1.5.2
Dynamic: description
Dynamic: description-content-type
